README
setup.py
docs/CONTRIBUTORS
docs/HISTORY
docs/LICENSE
dspace/__init__.py
dspace/metadata.py
dspace/repository.py
dspace.egg-info/PKG-INFO
dspace.egg-info/SOURCES.txt
dspace.egg-info/dependency_links.txt
dspace.egg-info/not-zip-safe
dspace.egg-info/requires.txt
dspace.egg-info/top_level.txt
dspace/sword/__init__.py
dspace/sword/collection.py
dspace/sword/item.py
dspace/sword/service.py
dspace/tests/__init__.py
dspace/tests/dspace_mets.xml
dspace/tests/metadata.py
dspace/tests/repository.py
dspace/tests/repository/all_identifiers.xml
dspace/tests/repository/all_records_001.xml
dspace/tests/repository/all_records_002.xml
dspace/tests/repository/collection_identifiers.xml
dspace/tests/repository/collection_records.xml
dspace/tests/repository/collections.xml
dspace/tests/repository/identify.xml
dspace/tests/repository/mapping.txt
dspace/tests/repository/record.xml