Metadata-Version: 1.0
Name: dspace
Version: 2.0
Summary: A python library for retrieving data from a DSpace repository.
Home-page: http://library.tamu.edu
Author: Texas A&M University Library
Author-email: webmaster@library.tamu.edu
License: UNKNOWN
Keywords: dspace oaipmh sword
Platform: UNKNOWN
Classifier: Programming Language :: Python
Classifier: Intended Audience :: Developers
Classifier: Intended Audience :: Education
Classifier: License :: OSI Approved :: Apache Software License
Classifier: Topic :: Software Development :: Libraries :: Python Modules
Classifier: Topic :: Education
Classifier: Development Status :: 5 - Production/Stable
